sumocfntester/__init__.py
sumocfntester/console.py
sumocfntester/process.py
sumocfntester/cleanup/__init__.py
sumocfntester/cleanup/cleanup.py
sumocfntester/cleanup/stack_delete.py
sumocfntester/common/__init__.py
sumocfntester/common/aws_client.py
sumocfntester/common/cf_utility.py
sumocfntester/common/logger.py
sumocfntester/common/objects.py
sumocfntester/common/report.py
sumocfntester/common/test_file_validator.py
sumocfntester/common/utils.py
sumocfntester/common/resources/parameter_file.schema
sumocfntester/common/resources/test_file.schema
sumocfntester/deploy/__init__.py
sumocfntester/deploy/deploy.py
sumocfntester/deploy/parameter_check.py
sumocfntester/deploy/stack_deploy.py
sumocfntester/postdeploy/__init__.py
sumocfntester/postdeploy/output_validation.py
sumocfntester/postdeploy/parameter_check.py
sumocfntester/postdeploy/postdeploy.py
sumocfntester/postdeploy/resource_validation.py
sumocfntester/predeploy/__init__.py
sumocfntester/predeploy/cfn-lint.py
sumocfntester/predeploy/cfn-nag.py
sumocfntester/predeploy/predeploy.py
tests/__init__.py
sumologic_cfn_tester-0.0.2.dist-info/LICENSE
sumologic_cfn_tester-0.0.2.dist-info/METADATA
sumologic_cfn_tester-0.0.2.dist-info/WHEEL
sumologic_cfn_tester-0.0.2.dist-info/entry_points.txt
sumologic_cfn_tester-0.0.2.dist-info/top_level.txt
sumologic_cfn_tester-0.0.2.dist-info/zip-safe
sumologic_cfn_tester-0.0.2.dist-info/RECORD
