Metadata-Version: 2.1
Name: sumologic-cfn-tester
Version: 0.0.2
Summary: Sumo Logic CloudFormation tester allows you to tests the CF for validation and deployments.
Home-page: https://github.com/SumoLogic/sumologic-aws-cloudformation-test
Author: SumoLogic
Author-email: it@sumologic.com, apps-team@sumologic.com
License: PSF
Keywords: sumologic cloudformation testing validation aws lint
Platform: UNKNOWN
Classifier: Development Status :: 4 - Beta
Classifier: Intended Audience :: Developers
Classifier: Programming Language :: Python :: 3.7
Classifier: Operating System :: OS Independent
Requires-Dist: cfn-lint (>=0.30.1)
Requires-Dist: jsonschema (>=3.2.0)
Requires-Dist: cfn-flip (>=1.2.3)
Requires-Dist: tabulate (>=0.8.6)
